{
  "images": [
    {
      "url": "https://raw.githubusercontent.com/nicomedinap/nicomedinap.github.io/master/Galeria/JWST/NGC3132/012.jpg",
      "description": "Descripción de la imagen 1",
      "tipo": "Nebulosa planetaria",
      "subtipo": "Subtipo",
      "versions": [
        {"url": "https://raw.githubusercontent.com/nicomedinap/nicomedinap.github.io/master/Galeria/JWST/NGC3132/021.jpg"},
        {"url": "https://raw.githubusercontent.com/nicomedinap/nicomedinap.github.io/master/Galeria/JWST/NGC3132/102.jpg"},
        {"url": "https://raw.githubusercontent.com/nicomedinap/nicomedinap.github.io/master/Galeria/JWST/NGC3132/120.jpg"},
        {"url": "https://raw.githubusercontent.com/nicomedinap/nicomedinap.github.io/master/Galeria/JWST/NGC3132/201.jpg"},
        {"url": "https://raw.githubusercontent.com/nicomedinap/nicomedinap.github.io/master/Galeria/JWST/NGC3132/210.jpg"}
      ]
    },
    {
      "url": "https://raw.githubusercontent.com/nicomedinap/nicomedinap.github.io/master/Galeria/JWST/NGC1566/012.jpg",
      "description": "Descripción de la imagen 2",
      "versions": [
        {"url": "https://raw.githubusercontent.com/nicomedinap/nicomedinap.github.io/master/Galeria/JWST/NGC1566/021.jpg"}
      ]
    }
  ]
}
